appmail/__init__.py
appmail/admin.py
appmail/apps.py
appmail/compat.py
appmail/forms.py
appmail/helpers.py
appmail/migrations/0001_initial.py
appmail/migrations/0002_add_template_description.py
appmail/migrations/0003_emailtemplate_test_context.py
appmail/migrations/0004_emailtemplate_is_active.py
appmail/migrations/0005_emailtemplate_from_email__reply_to.py
appmail/migrations/0006_emailtemplate_supports_attachments.py
appmail/migrations/__init__.py
appmail/models.py
appmail/settings.py
appmail/templates/admin/appmail/emailtemplate/change_form.html
appmail/templates/appmail/send_test_email.html
appmail/templates/base.html
appmail/templates/base.txt
appmail/urls.py
appmail/views.py
appmail-1.3.dist-info/LICENSE
appmail-1.3.dist-info/WHEEL
appmail-1.3.dist-info/METADATA
appmail-1.3.dist-info/RECORD
